{
    "username":"daps-devnet",
    "password":"test",
    "project":"dapscoin-216315",
    "zone":"us-east1-b",
    "publickeyfile":"/home/daps-devnet/.ssh/google_compute_engine",
    "main":{"name":"stg-1-blockexplorer", "address":"35.231.98.100"},
    "masternodes":[
        {"name":"stg-2-masternode-a", "address":"104.196.7.250"},
        {"name":"stg-3-masternode-b", "address":"35.229.54.148"}
    ],
    "stakingnodes":[
        {"name":"stg-4-stakingnode-c", "address":"35.227.81.1"},
        {"name":"stg-5-stakingnode-d", "address":"35.237.184.1"}
    ],
    "wallets":[
        {"name":"mncontrolwallet", "address":"207.148.88.148"}
    ],
    "coinamount":10000,
    "checkworkerinterval":600,
    "serveroption":"-testnet"
}